geolysis/__init__.py
geolysis/exceptions.py
geolysis/foundation.py
geolysis/soil_classifier.py
geolysis/spt.py
geolysis/bearing_capacity/__init__.py
geolysis/bearing_capacity/abc/__init__.py
geolysis/bearing_capacity/abc/_cohl/__init__.py
geolysis/bearing_capacity/abc/_cohl/_core.py
geolysis/bearing_capacity/abc/_cohl/bowles_abc.py
geolysis/bearing_capacity/abc/_cohl/meyerhof_abc.py
geolysis/bearing_capacity/abc/_cohl/terzaghi_abc.py
geolysis/bearing_capacity/ubc/__init__.py
geolysis/bearing_capacity/ubc/_core.py
geolysis/bearing_capacity/ubc/_terzaghi_ubc.py
geolysis/bearing_capacity/ubc/_vesic_ubc.py
geolysis/utils/__init__.py
geolysis/utils/math.py
geolysis-0.24.1.dist-info/licenses/LICENSE.txt
geolysis-0.24.1.dist-info/METADATA
geolysis-0.24.1.dist-info/WHEEL
geolysis-0.24.1.dist-info/top_level.txt
geolysis-0.24.1.dist-info/RECORD
