Metadata-Version: 2.4
Name: geolysis
Version: 0.24.1
Summary: geolysis is an opensource software for geotechnical engineering analysis and modeling.
Author-email: Patrick Boateng <boatengpato.pb@gmail.com>
License: MIT License
Project-URL: Homepage, https://docs.geolysis.io
Project-URL: Documentation, https://docs.geolysis.io
Project-URL: Repository, https://github.com/patrickboateng/geolysis
Project-URL: Discussions, https://github.com/patrickboateng/geolysis/discussions
Project-URL: Issue Tracker, https://github.com/patrickboateng/geolysis/issues
Keywords: geotechnical-engineering,soil-classification,bearing-capacity-analysis,standard-penetration-test-analysis
Classifier: Development Status :: 4 - Beta
Classifier: Intended Audience :: Developers
Classifier: Intended Audience :: Education
Classifier: Intended Audience :: Science/Research
Classifier: License :: OSI Approved :: MIT License
Classifier: Natural Language :: English
Classifier: Operating System :: OS Independent
Classifier: Programming Language :: Python :: 3.11
Classifier: Programming Language :: Python :: 3.12
Classifier: Programming Language :: Python :: Implementation :: CPython
Classifier: Topic :: Scientific/Engineering
Requires-Python: >=3.11
License-File: LICENSE.txt
Requires-Dist: func-validator
Provides-Extra: dev
Requires-Dist: pytest; extra == "dev"
Requires-Dist: pytest-cov; extra == "dev"
Requires-Dist: coverage; extra == "dev"
Dynamic: license-file
